ncube_sdk/__init__.py
ncube_sdk/client.py
ncube_sdk/http.py
ncube_sdk/validate.py
ncube_sdk-0.7.dist-info/LICENSE
ncube_sdk-0.7.dist-info/METADATA
ncube_sdk-0.7.dist-info/WHEEL
ncube_sdk-0.7.dist-info/top_level.txt
ncube_sdk-0.7.dist-info/RECORD
