Metadata-Version: 2.1
Name: ncube-sdk
Version: 0.7
Summary: N-Cube Ingest SDK
Home-page: https://github.com/ncubeanalytics/ncube-python/
Author: N Cube Single Member Private Company
Author-email: contact@n-cube.gr
License: Apache License, Version 2.0
Platform: UNKNOWN
Classifier: Programming Language :: Python
Classifier: License :: OSI Approved :: Apache Software License
Classifier: Operating System :: OS Independent
Requires-Python: >=2.7
License-File: LICENSE
Requires-Dist: requests <2.28 ; python_version < "3.0"
Requires-Dist: urllib3 <2 ; python_version < "3.0"
Requires-Dist: typing ; python_version < "3.5"
Requires-Dist: requests ; python_version >= "3.0"
Provides-Extra: jsonschema
Requires-Dist: jsonschema ; extra == 'jsonschema'
